sanskrit_grammar/NNExpression.py
sanskrit_grammar/__init__.py
sanskrit_grammar/ashtadhyayi_simulator.py
sanskrit_grammar/morphological_analyzer.py
sanskrit_grammar/morphology.py
sanskrit_grammar/samasa.py
sanskrit_grammar/sandhi.py
sanskrit_grammar/sanskrit_hindi_accessor.py
sanskrit_grammar/stem_generator.py
sanskrit_grammar/upasarga_pratyaya.py
sanskrit_grammar-0.4.0.dist-info/licenses/LICENSE
tests/__init__.py
tests/example.py
tests/test_fun.py
tests/test_morphological_analyzer.py
tests/test_morphology.py
tests/test_samasa.py
tests/test_sandhi.py
tests/test_sandhi_transformer.py
tests/test_sanskrit_hindi_accessor.py
tests/test_stem_generator.py
tests/test_upasarga_pratyaya.py
sanskrit_grammar-0.4.0.dist-info/METADATA
sanskrit_grammar-0.4.0.dist-info/WHEEL
sanskrit_grammar-0.4.0.dist-info/top_level.txt
sanskrit_grammar-0.4.0.dist-info/RECORD
