Metadata-Version: 2.4
Name: sanskrit-grammar
Version: 0.4.0
Summary: Python module provides functions to handle and manipulate various aspects of Sanskrit grammar, including word generation, prefixes etc
Home-page: https://github.com/saurabhchandrapatel/sanskrit-grammar
Author: Saurabh Chandra Patel
Author-email: vsaurabhaec@gmail.com
Classifier: Programming Language :: Python :: 3
Classifier: License :: OSI Approved :: MIT License
Requires-Python: >=3.6
License-File: LICENSE
Requires-Dist: matplotlib
Requires-Dist: networkx
Requires-Dist: pytesseract
Requires-Dist: Pillow
Dynamic: author
Dynamic: author-email
Dynamic: classifier
Dynamic: description
Dynamic: description-content-type
Dynamic: home-page
Dynamic: license-file
Dynamic: requires-dist
Dynamic: requires-python
Dynamic: summary
